myfunctions_andreibelous16/__init__.py
myfunctions_andreibelous16/math.py
myfunctions_andreibelous16-0.0.14.dist-info/METADATA
myfunctions_andreibelous16-0.0.14.dist-info/WHEEL
myfunctions_andreibelous16-0.0.14.dist-info/top_level.txt
myfunctions_andreibelous16-0.0.14.dist-info/RECORD
