Metadata-Version: 2.1
Name: myfunctions-andreibelous16
Version: 0.0.14
Summary: A description of your package
Home-page: https://github.com/Andreibelous16
Author: Andrei Belous
Author-email: andrewbelousit@gmail.com
License: MIT
Platform: UNKNOWN
Classifier: Programming Language :: Python :: 3
Classifier: License :: OSI Approved :: MIT License
Classifier: Operating System :: OS Independent
Requires-Python: >=3.6
